parktoma/vscconan/__init__.py
parktoma/vscconan/_vscconan.py
parktoma_vscconan-1.0.1.dist-info/LICENSE
parktoma_vscconan-1.0.1.dist-info/METADATA
parktoma_vscconan-1.0.1.dist-info/WHEEL
parktoma_vscconan-1.0.1.dist-info/top_level.txt
parktoma_vscconan-1.0.1.dist-info/RECORD
