Metadata-Version: 2.1
Name: parktoma-vscconan
Version: 1.0.1
Summary: Utility to update Visual Studio Code C++ Tools include paths from a conanfile
Home-page: https://github.com/parkertomatoes/parktoma-vscconan
Author: Parker Tomatoes
Author-email: parker.tomatoes@gmail.com
License: UNKNOWN
Platform: UNKNOWN
Classifier: Programming Language :: Python :: 3
Classifier: License :: OSI Approved :: MIT License
Classifier: Operating System :: OS Independent
Classifier: Intended Audience :: Developers
Classifier: Topic :: Software Development :: Build Tools
Requires-Python: >=3.5
